lsdelta.cp313-win_amd64.pyd
lsdelta/__init__.pyi
lsdelta/py.typed
lsdelta-0.9.1.dist-info/licenses/LICENSE.txt
lsdelta-0.9.1.dist-info/METADATA
lsdelta-0.9.1.dist-info/WHEEL
lsdelta-0.9.1.dist-info/top_level.txt
lsdelta-0.9.1.dist-info/RECORD
