Metadata-Version: 2.4
Name: lsdelta
Version: 0.9.1
Summary: Least Significant Digit Delta
Author-email: Hauke D <haukex@zero-g.net>
License-Expression: LGPL-3.0-or-later
Project-URL: Homepage, https://github.com/haukex/lsdelta
Project-URL: Bug Tracker, https://github.com/haukex/lsdelta/issues
Classifier: Programming Language :: Python :: 3
Classifier: Programming Language :: Python :: Implementation :: CPython
Classifier: Development Status :: 4 - Beta
Classifier: Topic :: Software Development :: Libraries
Requires-Python: >=3.10
License-File: LICENSE.txt
Dynamic: license-file
